<gml:featureMembers>
  <gml:featureMember>
    <Anleggsområde gml:id="Anleggsområde_58c892c4-f615-4317-935f-038765687265">
      <identifikasjon>
        <Identifikasjon>
          <lokalId>58c892c4-f615-4317-935f-038765687265</lokalId>
          <navnerom>http://data.geonorge.no/SOSI/FKB-Arealbruk</navnerom>
        </Identifikasjon>
      </identifikasjon>
      <oppdateringsdato>2021-08-26T21:08:00Z</oppdateringsdato>
      <datafangstdato>2021-08-26</datafangstdato>
      <kvalitet>
        <Posisjonskvalitet>
          <datafangstmetode>fot</datafangstmetode>
          <nøyaktighet>42</nøyaktighet>
          <synbarhet>2</synbarhet>
          <datafangstmetodeHøyde>fot</datafangstmetodeHøyde>
          <nøyaktighetHøyde>42</nøyaktighetHøyde>
        </Posisjonskvalitet>
      </kvalitet>
      <område>
        <gml:Polygon gml:id="Anleggsområde.0612.202.27.so.1" srsName="http://www.opengis.net/def/crs/epsg/0/5972" srsDimension="3">
          <gml:exterior>
            <gml:LinearRing>
              <gml:posList>568444.03 6661981.48 89.2 568506.41 6662009.49 91.2 568525.84 6661998.97 90.8 568529.64 6662001.85 91 568535.02 6662054.94 91.5 568476.33 6662067.85 90.5 568466.5 6662054.49 90.5 568444.03 6661981.48 89.2</gml:posList>
            </gml:LinearRing>
          </gml:exterior>
        </gml:Polygon>
      </område>
    </Anleggsområde>
  </gml:featureMember>
</gml:featureMembers>